{
  "entries": [
    {
      "id": "wsl-ubuntu-export",
      "enabled": false,
      "profile": [
        "dev"
      ],
      "phase": "backup",
      "category": "wsl",
      "tier": "T2",
      "method": "export-cmd",
      "command": "wsl --export Ubuntu-22.04 \"%PAYLOAD%\\wsl\\Ubuntu-22.04.tar\"",
      "target": "wsl/Ubuntu-22.04.tar",
      "requiresClosedProcesses": [],
      "secretHandling": "normal",
      "verify": {
        "exists": [],
        "maxSizeMB": 40000
      },
      "restore": {
        "order": 85,
        "mode": "command",
        "notes": "Use as reference when rebuilding the PC."
      },
      "description": "wsl-ubuntu-export: exports reference information into the payload for rebuilding the PC.",
      "uiWarning": "Large optional data; enable only after checking destination capacity."
    },
    {
      "id": "wsl-size-check",
      "enabled": true,
      "phase": "backup",
      "category": "wsl",
      "tier": "T3",
      "method": "manual-todo",
      "instructions": "Find the WSL distro VHDX path, check its size, and enable export only when the destination has enough free space.",
      "secretHandling": "normal",
      "restore": {
        "order": 84,
        "mode": "manual",
        "notes": "Manual review required after formatting."
      },
      "description": "Find the WSL distro VHDX path, check its size, and enable export only when the destination has enough free space.",
      "uiWarning": "Large optional data; enable only after checking destination capacity."
    }
  ]
}
